Metadata-Version: 2.1
Name: distributionsVM
Version: 0.2
Summary: Gaussian distributions
Home-page: UNKNOWN
Author: Victor Menoscal
Author-email: alfonso_menos@hotmail.com
License: UNKNOWN
Platform: UNKNOWN
